liviu_first_project/__init__.py
liviu_first_project-0.1.0.dist-info/METADATA
liviu_first_project-0.1.0.dist-info/WHEEL
liviu_first_project-0.1.0.dist-info/top_level.txt
liviu_first_project-0.1.0.dist-info/RECORD
