Metadata-Version: 2.1
Name: liviu-first-project
Version: 0.1.0
Summary: Say's hello from Liviu
Author: Liviu Andrei
Author-email: liviu.andrei.la@gmail.com
License: UNKNOWN
Platform: UNKNOWN
Requires-Dist: dinosay
